CHANGELOG.md
LICENSE
MANIFEST.in
README.rst
requirements-performance.txt
requirements.txt
setup.py
idsfree/__init__.py
idsfree/__main__.py
idsfree.egg-info/PKG-INFO
idsfree.egg-info/SOURCES.txt
idsfree.egg-info/dependency_links.txt
idsfree.egg-info/entry_points.txt
idsfree.egg-info/requires.txt
idsfree.egg-info/top_level.txt
idsfree/actions/__init__.py
idsfree/actions/cli.py
idsfree/actions/helpers.py
idsfree/actions/prepare/__init__.py
idsfree/actions/prepare/api.py
idsfree/actions/prepare/cli.py
idsfree/actions/prepare/console.py
idsfree/actions/prepare/model.py
idsfree/actions/runattacks/__init__.py
idsfree/actions/runattacks/api.py
idsfree/actions/runattacks/cli.py
idsfree/actions/runattacks/console.py
idsfree/actions/runattacks/helpers.py
idsfree/actions/runattacks/model.py
idsfree/actions/runattacks/results_parsers.py
idsfree/core/__init__.py
idsfree/core/exceptions.py
idsfree/core/helpers.py
idsfree/core/logger.py
idsfree/core/model.py
idsfree/core/shared_cmd_options.py
test/unittesting/__init__.py
test/unittesting/actions/__init__.py
test/unittesting/actions/default/__init__.py
test/unittesting/actions/default/api/__init__.py
test/unittesting/actions/default/api/test_run_idsfree.py
test/unittesting/actions/default/cli/__init__.py
test/unittesting/actions/default/cli/test_cli.py
test/unittesting/actions/default/cli/test_cli_info.py
test/unittesting/core/__init__.py
test/unittesting/core/helpers/__init__.py
test/unittesting/core/helpers/test_dict_to_obj.py
test/unittesting/core/logger/__init__.py
test/unittesting/core/logger/test_setup_logging.py
test/unittesting/core/shared_cmd_options/__init__.py
test/unittesting/core/shared_cmd_options/test_global_options.py
test/unittesting/mains/__init__.py
test/unittesting/mains/test_apitest_comparer_main.py