Metadata-Version: 1.1
Name: idsfree
Version: 1.0.0
Summary: IdsFree: Launch hacking tests in cloud providers securely, isolated and without raise security alerts in the provider
Home-page: https://github.com/bbva/idsfree
Author: cr0hn
Author-email: cr0hn@cr0hn.com
License: BSD
Platform: UNKNOWN
Classifier: Environment :: Console
Classifier: Intended Audience :: System Administrators
Classifier: Intended Audience :: Other Audience
Classifier: License :: OSI Approved :: BSD License
Classifier: Operating System :: MacOS
Classifier: Operating System :: Microsoft :: Windows
Classifier: Operating System :: POSIX
Classifier: Programming Language :: Python :: 3.5
Classifier: Topic :: Security
